setup.py
examples/simple_cli.py
examples/simple_receive.py
examples/simple_sender.py
wa_hack_cli/__init__.py
wa_hack_cli/wa_hack_cli.py
wa_hack_cli.egg-info/PKG-INFO
wa_hack_cli.egg-info/SOURCES.txt
wa_hack_cli.egg-info/dependency_links.txt
wa_hack_cli.egg-info/not-zip-safe
wa_hack_cli.egg-info/top_level.txt