Metadata-Version: 2.1
Name: wa-hack-cli
Version: 0.2
Summary: Client Library for the WhatsApp hack server.
Home-page: https://foo.bar
Author: grindsa
Author-email: grindelsack@gmail.com
License: GPL
Platform: any
Classifier: Programming Language :: Python
Classifier: Development Status :: 4 - Beta
Classifier: Natural Language :: German
Classifier: Intended Audience :: Developers
Classifier: License :: OSI Approved :: GNU General Public License v3 or later (GPLv3+)
Classifier: Operating System :: OS Independent
Classifier: Topic :: Software Development :: Libraries :: Python Modules
